Metadata-Version: 2.1
Name: keras-succ-reg-wrapper
Version: 0.4.0
Summary: A wrapper that slows down the updates of trainable weights
Home-page: https://github.com/CyberZHG/keras-succ-reg-wrapper
Author: CyberZHG
Author-email: CyberZHG@gmail.com
License: MIT
Platform: UNKNOWN
Classifier: Programming Language :: Python :: 2.7
Classifier: Programming Language :: Python :: 3.6
Classifier: License :: OSI Approved :: MIT License
Classifier: Operating System :: OS Independent
